funnelmap/__init__.py
funnelmap/formats.py
funnelmap/funnel.py
funnelmap/reading.py
funnelmap/saving.py
funnelmap/records/.registry.json
funnelmap-0.2.2.dist-info/METADATA
funnelmap-0.2.2.dist-info/WHEEL
funnelmap-0.2.2.dist-info/top_level.txt
funnelmap-0.2.2.dist-info/RECORD
