Metadata-Version: 2.1
Name: funnelmap
Version: 0.2.2
Summary: creating and saving many-to-one maps of memorable aliases to 'official' identifiers
Home-page: https://www.github.com/hotzsauce/funnel-dev
Author: hotzsauce
Author-email: githotz@gmail.com
License: MIT
Keywords: json,surjective,aliases,renaming
Platform: UNKNOWN
Classifier: Development Status :: 3 - Alpha
Classifier: License :: OSI Approved :: MIT License
Classifier: Programming Language :: Python :: 3
Classifier: Programming Language :: Python :: 3.7
Provides-Extra: dataframe
Requires-Dist: pandas ; extra == 'dataframe'
